urban_traffic/trafficv4.v
module smart_traffic_controller (
    input wire clk,
    input wire reset,

    // Traffic inputs
    input wire car_sensor,
    input wire pedestrian_req,
    input wire emergency,

    // Parking system
    input wire car_enter,
    input wire car_exit,

    // Time-based mode (early morning)
    input wire low_traffic_mode,

    // Outputs
    output reg [1:0] traffic_light,     // 00=RED, 01=YELLOW, 10=GREEN
    output reg pedestrian_green,
    output reg emergency_active,
    output reg [3:0] parking_slots
);

    // -------------------- State Encoding --------------------
    localparam s0_IDLE          = 3'b000;
    localparam s1_GREEN         = 3'b001;
    localparam s2_YELLOW        = 3'b010;
    localparam s3_RED           = 3'b011;
    localparam s4_EMERGENCY     = 3'b100;
    localparam s5_PEDESTRIAN    = 3'b101;
    localparam s6_YELLOW_BLINK  = 3'b110;

    reg [2:0] state, next_state;
    reg [3:0] timer;
    reg [3:0] green_limit;

    // -------------------- State Register --------------------
    always @(posedge clk or posedge reset) begin
        if (reset) begin
            state <= s0_IDLE;
            timer <= 0;
            parking_slots <= 4'd10;
        end else begin
            state <= next_state;

            if (state != next_state)
                timer <= 0;
            else
                timer <= timer + 1;
        end
    end

    // -------------------- Parking Slot Management --------------------
    always @(posedge clk) begin
        if (!reset) begin
            if (car_enter && parking_slots > 0)
                parking_slots <= parking_slots - 1;
            else if (car_exit && parking_slots < 10)
                parking_slots <= parking_slots + 1;
        end
    end

    // -------------------- Adaptive Green Timing --------------------
    always @(*) begin
        if (!car_sensor)
            green_limit = 3;   // low traffic → short green
        else
            green_limit = 6;   // normal traffic
    end

    // -------------------- Next State Logic --------------------
    always @(*) begin
        next_state = state;

        case (state)

            s0_IDLE:
                if (emergency)
                    next_state = s4_EMERGENCY;
                else if (low_traffic_mode)
                    next_state = s6_YELLOW_BLINK;
                else if (pedestrian_req)
                    next_state = s5_PEDESTRIAN;
                else if (car_sensor)
                    next_state = s1_GREEN;

            s1_GREEN:
                if (emergency)
                    next_state = s4_EMERGENCY;
                else if (timer >= green_limit)
                    next_state = s2_YELLOW;

            s2_YELLOW:
                if (timer == 2)
                    next_state = s3_RED;

            s3_RED:
                if (timer == 3)
                    next_state = s0_IDLE;

            s5_PEDESTRIAN:
                if (timer == 3)
                    next_state = s0_IDLE;

            s4_EMERGENCY:
                if (!emergency)
                    next_state = s0_IDLE;

            s6_YELLOW_BLINK:
                if (!low_traffic_mode)
                    next_state = s0_IDLE;

            default:
                next_state = s0_IDLE;
        endcase
    end

    // -------------------- Output Logic --------------------
    always @(*) begin
        traffic_light = 2'b00;
        pedestrian_green = 0;
        emergency_active = 0;

        case (state)

            s1_GREEN:
                traffic_light = 2'b10;

            s2_YELLOW:
                traffic_light = 2'b01;

            s3_RED:
                traffic_light = 2'b00;

            s5_PEDESTRIAN: begin
                traffic_light = 2'b00;
                pedestrian_green = 1;
            end

            s4_EMERGENCY: begin
                traffic_light = 2'b10;  // force GREEN
                emergency_active = 1;
            end

            s6_YELLOW_BLINK:
                traffic_light = (timer[0]) ? 2'b01 : 2'b00;

        endcase
    end

endmodule

urban_traffic/tb_trafficv4.v
`timescale 1ns/1ps

module tb_smart_traffic_controller;

    // Testbench signals
    reg clk;
    reg reset;

    reg car_sensor;
    reg pedestrian_req;
    reg emergency;

    reg car_enter;
    reg car_exit;

    reg low_traffic_mode;

    wire [1:0] traffic_light;
    wire pedestrian_green;
    wire emergency_active;
    wire [3:0] parking_slots;

    // -------------------- DUT Instantiation --------------------
    smart_traffic_controller DUT (
        .clk(clk),
        .reset(reset),
        .car_sensor(car_sensor),
        .pedestrian_req(pedestrian_req),
        .emergency(emergency),
        .car_enter(car_enter),
        .car_exit(car_exit),
        .low_traffic_mode(low_traffic_mode),
        .traffic_light(traffic_light),
        .pedestrian_green(pedestrian_green),
        .emergency_active(emergency_active),
        .parking_slots(parking_slots)
    );

    // -------------------- Clock Generation --------------------
    initial begin
        clk = 0;
        forever #5 clk = ~clk;   // 10ns clock period
    end

    // -------------------- Stimulus --------------------
    initial begin
        // Initialize inputs
        reset = 1;
        car_sensor = 0;
        pedestrian_req = 0;
        emergency = 0;
        car_enter = 0;
        car_exit = 0;
        low_traffic_mode = 0;

        // Waveform dump
        $dumpfile("smart_traffic.vcd");
        $dumpvars(0, tb_smart_traffic_controller);

        // Reset pulse
        #20 reset = 0;

        // ---------------- NORMAL TRAFFIC ----------------
        #20 car_sensor = 1;        // vehicle detected
        #100 car_sensor = 0;

        // ---------------- PEDESTRIAN REQUEST ----------------
	// Pedestrian request DURING vehicle green
        #30 pedestrian_req = 1;
        #20 pedestrian_req = 0;
	// Pedestrian request AFTER full traffic cycle
	#120 pedestrian_req = 1;
	#20  pedestrian_req = 0;


        // ---------------- PARKING ENTRY ----------------
        #30 car_enter = 1;
        #10 car_enter = 0;

        // ---------------- PARKING EXIT ----------------
        #40 car_exit = 1;
        #10 car_exit = 0;

        // ---------------- EMERGENCY OVERRIDE ----------------
        #50 emergency = 1;
        #40 emergency = 0;

        // ---------------- LOW TRAFFIC MODE (EARLY MORNING) ----------------
        #50 low_traffic_mode = 1;
        #100 low_traffic_mode = 0;

        // End simulation
        #200 $finish;
    end

endmodule

urban_traffic/trafficv4.vcd
$date
	Sun Dec 14 11:11:53 2025
$end
$version
	Icarus Verilog
$end
$timescale
	1ps
$end
$scope module tb_smart_traffic_controller $end
$var wire 2 ! traffic_light [1:0] $end
$var wire 1 " pedestrian_green $end
$var wire 4 # parking_slots [3:0] $end
$var wire 1 $ emergency_active $end
$var reg 1 % car_enter $end
$var reg 1 & car_exit $end
$var reg 1 ' car_sensor $end
$var reg 1 ( clk $end
$var reg 1 ) emergency $end
$var reg 1 * low_traffic_mode $end
$var reg 1 + pedestrian_req $end
$var reg 1 , reset $end
$scope module DUT $end
$var wire 1 % car_enter $end
$var wire 1 & car_exit $end
$var wire 1 ' car_sensor $end
$var wire 1 ( clk $end
$var wire 1 ) emergency $end
$var wire 1 * low_traffic_mode $end
$var wire 1 + pedestrian_req $end
$var wire 1 , reset $end
$var parameter 3 - s0_IDLE $end
$var parameter 3 . s1_GREEN $end
$var parameter 3 / s2_YELLOW $end
$var parameter 3 0 s3_RED $end
$var parameter 3 1 s4_EMERGENCY $end
$var parameter 3 2 s5_PEDESTRIAN $end
$var parameter 3 3 s6_YELLOW_BLINK $end
$var reg 1 $ emergency_active $end
$var reg 4 4 green_limit [3:0] $end
$var reg 3 5 next_state [2:0] $end
$var reg 4 6 parking_slots [3:0] $end
$var reg 1 " pedestrian_green $end
$var reg 3 7 state [2:0] $end
$var reg 4 8 timer [3:0] $end
$var reg 2 9 traffic_light [1:0] $end
$upscope $end
$upscope $end
$enddefinitions $end
$comment Show the parameter values. $end
$dumpall
b110 3
b101 2
b100 1
b11 0
b10 /
b1 .
b0 -
$end
#0
$dumpvars
b0 9
b0 8
b0 7
b1010 6
b0 5
b11 4
1,
0+
0*
0)
0(
0'
0&
0%
0$
b1010 #
0"
b0 !
$end
#5000
1(
#10000
0(
#15000
1(
#20000
0(
0,
#25000
b1 8
1(
#30000
0(
#35000
b10 8
1(
#40000
b1 5
b110 4
0(
1'
#45000
b10 !
b10 9
b0 8
b1 7
1(
#50000
0(
#55000
b10 !
b10 9
b1 8
1(
#60000
0(
#65000
b10 !
b10 9
b10 8
1(
#70000
0(
#75000
b10 !
b10 9
b11 8
1(
#80000
0(
#85000
b10 !
b10 9
b100 8
1(
#90000
0(
#95000
b10 !
b10 9
b101 8
1(
#100000
0(
#105000
b10 !
b10 9
b10 5
b110 8
1(
#110000
0(
#115000
b1 !
b1 9
b0 8
b10 7
1(
#120000
0(
#125000
b1 !
b1 9
b1 8
1(
#130000
0(
#135000
b1 !
b1 9
b11 5
b10 8
1(
#140000
b11 5
b11 4
0(
0'
#145000
b0 !
b0 9
b0 8
b11 7
1(
#150000
0(
#155000
b1 8
1(
#160000
0(
#165000
b10 8
1(
#170000
0(
1+
#175000
b0 5
b11 8
1(
#180000
0(
#185000
b101 5
b0 8
b0 7
1(
#190000
b0 5
0(
0+
#195000
b1 8
1(
#200000
0(
#205000
b10 8
1(
#210000
0(
#215000
b11 8
1(
#220000
0(
#225000
b100 8
1(
#230000
0(
#235000
b101 8
1(
#240000
0(
#245000
b110 8
1(
#250000
0(
#255000
b111 8
1(
#260000
0(
#265000
b1000 8
1(
#270000
0(
#275000
b1001 8
1(
#280000
0(
#285000
b1010 8
1(
#290000
0(
#295000
b1011 8
1(
#300000
0(
#305000
b1100 8
1(
#310000
b101 5
0(
1+
#315000
1"
b0 8
b101 7
1(
#320000
0(
#325000
1"
b1 8
1(
#330000
0(
0+
#335000
1"
b10 8
1(
#340000
0(
#345000
1"
b0 5
b11 8
1(
#350000
0(
#355000
0"
b0 8
b0 7
1(
#360000
0(
1%
#365000
b1001 #
b1001 6
b1 8
1(
#370000
0(
0%
#375000
b10 8
1(
#380000
0(
#385000
b11 8
1(
#390000
0(
#395000
b100 8
1(
#400000
0(
#405000
b101 8
1(
#410000
0(
1&
#415000
b1010 #
b1010 6
b110 8
1(
#420000
0(
0&
#425000
b111 8
1(
#430000
0(
#435000
b1000 8
1(
#440000
0(
#445000
b1001 8
1(
#450000
0(
#455000
b1010 8
1(
#460000
0(
#465000
b1011 8
1(
#470000
b100 5
0(
1)
#475000
1$
b10 !
b10 9
b0 8
b100 7
1(
#480000
0(
#485000
1$
b10 !
b10 9
b1 8
1(
#490000
0(
#495000
1$
b10 !
b10 9
b10 8
1(
#500000
0(
#505000
1$
b10 !
b10 9
b11 8
1(
#510000
b0 5
0(
0)
#515000
0$
b0 !
b0 9
b0 8
b0 7
1(
#520000
0(
#525000
b1 8
1(
#530000
0(
#535000
b10 8
1(
#540000
0(
#545000
b11 8
1(
#550000
0(
#555000
b100 8
1(
#560000
b110 5
0(
1*
#565000
b0 8
b110 7
1(
#570000
0(
#575000
b1 !
b1 9
b1 8
1(
#580000
0(
#585000
b0 !
b0 9
b10 8
1(
#590000
0(
#595000
b1 !
b1 9
b11 8
1(
#600000
0(
#605000
b0 !
b0 9
b100 8
1(
#610000
0(
#615000
b1 !
b1 9
b101 8
1(
#620000
0(
#625000
b0 !
b0 9
b110 8
1(
#630000
0(
#635000
b1 !
b1 9
b111 8
1(
#640000
0(
#645000
b0 !
b0 9
b1000 8
1(
#650000
0(
#655000
b1 !
b1 9
b1001 8
1(
#660000
b0 5
0(
0*
#665000
b0 !
b0 9
b0 8
b0 7
1(
#670000
0(
#675000
b1 8
1(
#680000
0(
#685000
b10 8
1(
#690000
0(
#695000
b11 8
1(
#700000
0(
#705000
b100 8
1(
#710000
0(
#715000
b101 8
1(
#720000
0(
#725000
b110 8
1(
#730000
0(
#735000
b111 8
1(
#740000
0(
#745000
b1000 8
1(
#750000
0(
#755000
b1001 8
1(
#760000
0(
#765000
b1010 8
1(
#770000
0(
#775000
b1011 8
1(
#780000
0(
#785000
b1100 8
1(
#790000
0(
#795000
b1101 8
1(
#800000
0(
#805000
b1110 8
1(
#810000
0(
#815000
b1111 8
1(
#820000
0(
#825000
b0 8
1(
#830000
0(
#835000
b1 8
1(
#840000
0(
#845000
b10 8
1(
#850000
0(
#855000
b11 8
1(
